batch_work/__init__.py
batch_work/bw_delempty.py
batch_work/bw_rename.py
batch_work/bw_sort.py
batch_work/main.py
batch_work-0.2.3.dist-info/LICENSE
batch_work-0.2.3.dist-info/METADATA
batch_work-0.2.3.dist-info/WHEEL
batch_work-0.2.3.dist-info/entry_points.txt
batch_work-0.2.3.dist-info/top_level.txt
batch_work-0.2.3.dist-info/RECORD
