Metadata-Version: 2.1
Name: batch-work
Version: 0.2.3
Summary: CLI tool to organize and rename files.
Author: Ugyen Norbu
Author-email: unorbu2007@gmail.com
License: MIT
License-File: LICENSE
Requires-Dist: tree
